gerrit_sync/__init__.py
gerrit_sync/__main__.py
gerrit_sync/cli.py
gerrit_sync/util_gerrit.py
gerrit_sync/util_logging.py
gerrit_sync-0.23.dist-info/LICENSE
gerrit_sync-0.23.dist-info/METADATA
gerrit_sync-0.23.dist-info/WHEEL
gerrit_sync-0.23.dist-info/entry_points.txt
gerrit_sync-0.23.dist-info/top_level.txt
gerrit_sync-0.23.dist-info/RECORD
