Metadata-Version: 2.1
Name: gerrit-sync
Version: 0.23
Summary: a command line tool to easily clone gerrit repositories in bulk.
Home-page: https://github.com/fcivaner/gerrit-sync
Author: Fırat Civaner
Author-email: fcivaner@gmail.com
License: MIT License
Keywords: repository gerrit git clone sync
Platform: UNKNOWN
Classifier: Programming Language :: Python :: 3
Classifier: License :: OSI Approved :: MIT License
Classifier: Operating System :: OS Independent
Requires-Dist: pygerrit2
Requires-Dist: requests
